MANIFEST.in
README.rst
setup.py
opps/__init__.py
opps/polls/__init__.py
opps/polls/admin.py
opps/polls/forms.py
opps/polls/models.py
opps/polls/search_indexes.py
opps/polls/tests.py
opps/polls/urls.py
opps/polls/utils.py
opps/polls/views.py
opps/polls/widgets.py
opps/polls/migrations/0001_initial.py
opps/polls/migrations/0002_auto__add_field_pollbox_channel_name__add_field_pollbox_channel_long_s.py
opps/polls/migrations/0003_auto__del_unique_poll_slug__add_field_pollboxpolls_date_available__add.py
opps/polls/migrations/0004_auto__add_unique_poll_site_slug.py
opps/polls/migrations/__init__.py
opps/polls/templates/polls/poll_closed.html
opps/polls/templates/polls/poll_detail.html
opps/polls/templates/polls/poll_list.html
opps/polls/templates/polls/poll_result.html
opps/polls/templates/polls/poll_voted.html
opps/polls/templatetags/__init__.py
opps/polls/templatetags/polls_tags.py
opps_polls.egg-info/PKG-INFO
opps_polls.egg-info/SOURCES.txt
opps_polls.egg-info/dependency_links.txt
opps_polls.egg-info/namespace_packages.txt
opps_polls.egg-info/requires.txt
opps_polls.egg-info/top_level.txt