Metadata-Version: 1.0
Name: opps-polls
Version: 0.1.5
Summary: Poll App for Opps CMS
Home-page: http://oppsproject.org
Author: Bruno Cezar Rocha
Author-email: rochacbruno@gmail.com
License: MIT License
Download-URL: https://github.com/opps/opps-polls/tarball/master
Keywords: poll opps cms django apps magazines websites
Platform: UNKNOWN
Classifier: Development Status :: 4 - Beta
Classifier: Intended Audience :: Developers
Classifier: License :: OSI Approved :: MIT License
Classifier: Operating System :: OS Independent
Classifier: Framework :: Django
Classifier: Programming Language :: Python
Classifier: Programming Language :: Python :: 2.7
Classifier: Operating System :: OS Independent
Classifier: Topic :: Internet :: WWW/HTTP :: Dynamic Content
Classifier: Topic :: Software Development :: Libraries :: Python Modules
